infoindia/__init__.py
infoindia/infoindia.py
infoindia-1.1.11.dist-info/METADATA
infoindia-1.1.11.dist-info/WHEEL
infoindia-1.1.11.dist-info/top_level.txt
infoindia-1.1.11.dist-info/RECORD
