Metadata-Version: 2.1
Name: infoindia
Version: 1.1.11
Summary: Wrapper for State Data APIs
Home-page: https://github.com/NarutoUzumvki/state_data_api
Author: Vijay Chouhan
Author-email: vijay977364@gmail.com
Classifier: Programming Language :: Python :: 3
Classifier: License :: OSI Approved :: MIT License
Classifier: Operating System :: OS Independent
Requires-Dist: requests
